sani_nlu/__init__.py
sani_nlu/constants.py
sani_nlu/utils.py
sani_nlu/extractors/__init__.py
sani_nlu/extractors/flair_extractor.py
sani_nlu/extractors/overlap_extractor.py
sani_nlu/tokenizers/__init__.py
sani_nlu/tokenizers/vietnamese_tokenizer.py
sani_nlu-1.0.3.dist-info/METADATA
sani_nlu-1.0.3.dist-info/WHEEL
sani_nlu-1.0.3.dist-info/top_level.txt
sani_nlu-1.0.3.dist-info/RECORD
