Metadata-Version: 2.1
Name: sani-nlu
Version: 1.0.3
Summary: Sani-NLU is a library to implement NLU component for Sani chatbot.
Home-page: https://github.com/phamnam-mta/sani_nlu.git
Author: namph
Author-email: phamnam.mta@gmail.com
License: UNKNOWN
Keywords: sani_nlu
Platform: UNKNOWN
Requires-Python: >=3.6
Requires-Dist: rasa (==2.8.0)
Requires-Dist: flair (==0.8.0.post1)
